aPyNBT/__init__.py
aPyNBT/nbt.py
aPyNBT/region.py
aPyNBT-0.3a0.dist-info/LICENSE
aPyNBT-0.3a0.dist-info/METADATA
aPyNBT-0.3a0.dist-info/WHEEL
aPyNBT-0.3a0.dist-info/top_level.txt
aPyNBT-0.3a0.dist-info/RECORD
